{"_via_settings":{"ui":{"annotation_editor_height":25,"annotation_editor_fontsize":0.8,"leftsidebar_width":18,"image_grid":{"img_height":80,"rshape_fill":"none","rshape_fill_opacity":0.3,"rshape_stroke":"yellow","rshape_stroke_width":2,"show_region_shape":true,"show_image_policy":"all"},"image":{"region_label":"name","region_color":"__via_default_region_color__","region_label_font":"12px Sans","on_image_annotation_editor_placement":"NEAR_REGION"}},"core":{"buffer_size":"18","filepath":{},"default_filepath":""},"project":{"name":"C64 250407 PCB Replica 1of2"}},"_via_img_metadata":{"C64 250407 PCB Replica 1of2.jpg1200089":{"filename":"C64 250407 PCB Replica 1of2.jpg","size":1873634,"regions":[{"shape_attributes":{"name":"rect","x":374,"y":292,"width":29,"height":202},"region_attributes":{"name":"CN4"}},{"shape_attributes":{"name":"rect","x":551,"y":446,"width":76,"height":87},"region_attributes":{"name":"C47"}},{"shape_attributes":{"name":"rect","x":1487,"y":378,"width":87,"height":104},"region_attributes":{"name":"C9"}},{"shape_attributes":{"name":"rect","x":1374,"y":378,"width":108,"height":104},"region_attributes":{"name":"C8"}},{"shape_attributes":{"name":"rect","x":2408,"y":350,"width":99,"height":74},"region_attributes":{"name":"C18"}},{"shape_attributes":{"name":"rect","x":3429,"y":885,"width":98,"height":54},"region_attributes":{"name":"C82"}},{"shape_attributes":{"name":"rect","x":3356,"y":968,"width":100,"height":143},"region_attributes":{"name":"U29"}},{"shape_attributes":{"name":"rect","x":2999,"y":974,"width":92,"height":70},"region_attributes":{"name":"C68"}},{"shape_attributes":{"name":"rect","x":2863,"y":960,"width":100,"height":84},"region_attributes":{"name":"C107"}},{"shape_attributes":{"name":"rect","x":2776,"y":933,"width":86,"height":89},"region_attributes":{"name":"Y1"}},{"shape_attributes":{"name":"rect","x":2677,"y":872,"width":99,"height":60},"region_attributes":{"name":"C67"}},{"shape_attributes":{"name":"rect","x":2359,"y":870,"width":95,"height":100},"region_attributes":{"name":"C65"}},{"shape_attributes":{"name":"rect","x":2457,"y":871,"width":90,"height":77},"region_attributes":{"name":"C66"}},{"shape_attributes":{"name":"rect","x":2793,"y":1128,"width":231,"height":101},"region_attributes":{"name":"U31"}},{"shape_attributes":{"name":"rect","x":3027,"y":1191,"width":98,"height":128},"region_attributes":{"name":"C108"}},{"shape_attributes":{"name":"rect","x":2720,"y":1027,"width":141,"height":70},"region_attributes":{"name":"C70"}},{"shape_attributes":{"name":"rect","x":1600,"y":394,"width":229,"height":994},"region_attributes":{"name":"U7"}},{"shape_attributes":{"name":"rect","x":533,"y":552,"width":259,"height":115},"region_attributes":{"name":"U28"}},{"shape_attributes":{"name":"rect","x":374,"y":2280,"width":30,"height":792},"region_attributes":{"name":"CN2"}},{"shape_attributes":{"name":"rect","x":373,"y":839,"width":30,"height":288},"region_attributes":{"name":"CN8"}},{"shape_attributes":{"name":"rect","x":374,"y":1157,"width":30,"height":288},"region_attributes":{"name":"CN9"}},{"shape_attributes":{"name":"rect","x":1460,"y":1372,"width":87,"height":67},"region_attributes":{"name":"C2"}},{"shape_attributes":{"name":"rect","x":1598,"y":1444,"width":230,"height":606},"region_attributes":{"name":"U1"}},{"shape_attributes":{"name":"rect","x":3153,"y":1373,"width":287,"height":100},"region_attributes":{"name":"U30"}},{"shape_attributes":{"name":"rect","x":3396,"y":1219,"width":122,"height":60},"region_attributes":{"name":"C83"}},{"shape_attributes":{"name":"rect","x":3499,"y":1320,"width":101,"height":59},"region_attributes":{"name":"C74"}},{"shape_attributes":{"name":"rect","x":3602,"y":1416,"width":99,"height":144},"region_attributes":{"name":"U29"}},{"shape_attributes":{"name":"rect","x":3931,"y":1430,"width":58,"height":87},"region_attributes":{"name":"U32"}},{"shape_attributes":{"name":"rect","x":3817,"y":1430,"width":58,"height":87},"region_attributes":{"name":"U32"}},{"shape_attributes":{"name":"rect","x":4252,"y":1491,"width":111,"height":78},"region_attributes":{"name":"U32"}},{"shape_attributes":{"name":"rect","x":4309,"y":1406,"width":98,"height":62},"region_attributes":{"name":"C56"}},{"shape_attributes":{"name":"rect","x":4408,"y":1267,"width":96,"height":58},"region_attributes":{"name":"C84"}},{"shape_attributes":{"name":"rect","x":4224,"y":1296,"width":69,"height":102},"region_attributes":{"name":"C85"}},{"shape_attributes":{"name":"rect","x":3380,"y":2010,"width":106,"height":50},"region_attributes":{"name":"C39"}},{"shape_attributes":{"name":"rect","x":2692,"y":1795,"width":81,"height":110},"region_attributes":{"name":"C86"}},{"shape_attributes":{"name":"rect","x":2622,"y":1919,"width":229,"height":101},"region_attributes":{"name":"U31"}},{"shape_attributes":{"name":"rect","x":1141,"y":2320,"width":169,"height":81},"region_attributes":{"name":"U8"}},{"shape_attributes":{"name":"rect","x":1140,"y":2136,"width":169,"height":81},"region_attributes":{"name":"U8"}},{"shape_attributes":{"name":"rect","x":1140,"y":2220,"width":169,"height":81},"region_attributes":{"name":"U8"}},{"shape_attributes":{"name":"rect","x":1600,"y":2193,"width":228,"height":605},"region_attributes":{"name":"U2"}},{"shape_attributes":{"name":"rect","x":1782,"y":2089,"width":79,"height":86},"region_attributes":{"name":"C3"}},{"shape_attributes":{"name":"rect","x":2400,"y":2335,"width":98,"height":84},"region_attributes":{"name":"C57"}},{"shape_attributes":{"name":"rect","x":2304,"y":2328,"width":94,"height":65},"region_attributes":{"name":"C59"}},{"shape_attributes":{"name":"rect","x":2492,"y":2525,"width":114,"height":57},"region_attributes":{"name":"VR2"}},{"shape_attributes":{"name":"rect","x":2612,"y":2332,"width":88,"height":69},"region_attributes":{"name":"C89"}},{"shape_attributes":{"name":"rect","x":2702,"y":2338,"width":120,"height":93},"region_attributes":{"name":"C88"}},{"shape_attributes":{"name":"rect","x":2867,"y":2235,"width":82,"height":115},"region_attributes":{"name":"C90"}},{"shape_attributes":{"name":"rect","x":2491,"y":2294,"width":114,"height":56},"region_attributes":{"name":"VR1"}},{"shape_attributes":{"name":"rect","x":2290,"y":2565,"width":109,"height":62},"region_attributes":{"name":"C103"}},{"shape_attributes":{"name":"rect","x":2400,"y":2570,"width":100,"height":88},"region_attributes":{"name":"C102"}},{"shape_attributes":{"name":"rect","x":2611,"y":2565,"width":88,"height":58},"region_attributes":{"name":"C95"}},{"shape_attributes":{"name":"rect","x":2701,"y":2568,"width":124,"height":88},"region_attributes":{"name":"C19"}},{"shape_attributes":{"name":"rect","x":3226,"y":2064,"width":115,"height":202},"region_attributes":{"name":"U20"}},{"shape_attributes":{"name":"rect","x":3043,"y":2125,"width":111,"height":73},"region_attributes":{"name":"C24"}},{"shape_attributes":{"name":"rect","x":3155,"y":2270,"width":117,"height":51},"region_attributes":{"name":"C105"}},{"shape_attributes":{"name":"rect","x":2709,"y":2124,"width":118,"height":61},"region_attributes":{"name":"C36"}},{"shape_attributes":{"name":"rect","x":3429,"y":2085,"width":134,"height":80},"region_attributes":{"name":"U8"}},{"shape_attributes":{"name":"rect","x":3262,"y":2676,"width":92,"height":60},"region_attributes":{"name":"C92"}},{"shape_attributes":{"name":"rect","x":3139,"y":2678,"width":120,"height":73},"region_attributes":{"name":"C91"}},{"shape_attributes":{"name":"rect","x":3128,"y":2757,"width":84,"height":99},"region_attributes":{"name":"C100"}},{"shape_attributes":{"name":"rect","x":2987,"y":2752,"width":50,"height":99},"region_attributes":{"name":"C99"}},{"shape_attributes":{"name":"rect","x":2875,"y":2736,"width":68,"height":117},"region_attributes":{"name":"C21"}},{"shape_attributes":{"name":"rect","x":2674,"y":2807,"width":105,"height":59},"region_attributes":{"name":"C98"}},{"shape_attributes":{"name":"rect","x":547,"y":2793,"width":87,"height":62},"region_attributes":{"name":"C96"}},{"shape_attributes":{"name":"rect","x":375,"y":1474,"width":30,"height":632},"region_attributes":{"name":"CN1"}},{"shape_attributes":{"name":"rect","x":905,"y":3040,"width":96,"height":83},"region_attributes":{"name":"C23"}},{"shape_attributes":{"name":"rect","x":1067,"y":2999,"width":114,"height":202},"region_attributes":{"name":"U20"}},{"shape_attributes":{"name":"rect","x":1221,"y":2941,"width":66,"height":83},"region_attributes":{"name":"C22"}},{"shape_attributes":{"name":"rect","x":1256,"y":2999,"width":159,"height":97},"region_attributes":{"name":"U8"}},{"shape_attributes":{"name":"rect","x":1842,"y":2991,"width":59,"height":92},"region_attributes":{"name":"C46"}},{"shape_attributes":{"name":"rect","x":1875,"y":3055,"width":114,"height":111},"region_attributes":{"name":"U27"}},{"shape_attributes":{"name":"rect","x":2173,"y":3127,"width":123,"height":83},"region_attributes":{"name":"C200"}},{"shape_attributes":{"name":"rect","x":2477,"y":3086,"width":88,"height":29},"region_attributes":{"name":"CN10"}},{"shape_attributes":{"name":"rect","x":2870,"y":2887,"width":75,"height":113},"region_attributes":{"name":"C20"}},{"shape_attributes":{"name":"rect","x":3136,"y":2938,"width":65,"height":100},"region_attributes":{"name":"C97"}},{"shape_attributes":{"name":"rect","x":2823,"y":3130,"width":432,"height":28},"region_attributes":{"name":"CN7"}},{"shape_attributes":{"name":"rect","x":2953,"y":538,"width":27,"height":260},"region_attributes":{"name":"CN3"}},{"shape_attributes":{"name":"rect","x":2809,"y":753,"width":87,"height":55},"region_attributes":{"name":"C1"}},{"shape_attributes":{"name":"rect","x":786,"y":3144,"width":70,"height":106},"region_attributes":{"name":"C38"}},{"shape_attributes":{"name":"rect","x":2800,"y":2702,"width":69,"height":76},"region_attributes":{"name":"F1"}},{"shape_attributes":{"name":"rect","x":2923,"y":3024,"width":200,"height":100},"region_attributes":{"name":"SW1"}},{"shape_attributes":{"name":"rect","x":821,"y":219,"width":88,"height":94},"region_attributes":{"name":"RP3"}},{"shape_attributes":{"name":"rect","x":486,"y":770,"width":68,"height":58},"region_attributes":{"name":"FB18"}},{"shape_attributes":{"name":"rect","x":878,"y":2049,"width":60,"height":71},"region_attributes":{"name":"R29"}},{"shape_attributes":{"name":"rect","x":774,"y":2109,"width":166,"height":41},"region_attributes":{"name":"R30"}},{"shape_attributes":{"name":"rect","x":870,"y":2150,"width":67,"height":64},"region_attributes":{"name":"R28"}},{"shape_attributes":{"name":"rect","x":766,"y":2249,"width":158,"height":28},"region_attributes":{"name":"CR102"}},{"shape_attributes":{"name":"rect","x":766,"y":2222,"width":158,"height":28},"region_attributes":{"name":"CR100"}},{"shape_attributes":{"name":"rect","x":958,"y":2028,"width":52,"height":65},"region_attributes":{"name":"FB7"}},{"shape_attributes":{"name":"rect","x":498,"y":2201,"width":176,"height":87},"region_attributes":{"name":"RP3"}},{"shape_attributes":{"name":"rect","x":702,"y":3078,"width":78,"height":65},"region_attributes":{"name":"R41"}},{"shape_attributes":{"name":"rect","x":802,"y":3083,"width":91,"height":60},"region_attributes":{"name":"R35"}},{"shape_attributes":{"name":"rect","x":947,"y":2982,"width":78,"height":59},"region_attributes":{"name":"R33"}},{"shape_attributes":{"name":"rect","x":1452,"y":2928,"width":104,"height":86},"region_attributes":{"name":"RP3"}},{"shape_attributes":{"name":"rect","x":1768,"y":2923,"width":67,"height":79},"region_attributes":{"name":"R37"}},{"shape_attributes":{"name":"rect","x":1180,"y":2061,"width":199,"height":31},"region_attributes":{"name":"CR103"}},{"shape_attributes":{"name":"rect","x":1180,"y":2033,"width":199,"height":31},"region_attributes":{"name":"CR101"}},{"shape_attributes":{"name":"rect","x":1019,"y":2030,"width":49,"height":65},"region_attributes":{"name":"FB9"}},{"shape_attributes":{"name":"rect","x":1078,"y":2031,"width":45,"height":63},"region_attributes":{"name":"FB8"}},{"shape_attributes":{"name":"rect","x":1399,"y":1256,"width":101,"height":85},"region_attributes":{"name":"RP3"}},{"shape_attributes":{"name":"rect","x":1545,"y":225,"width":83,"height":54},"region_attributes":{"name":"R1"}},{"shape_attributes":{"name":"rect","x":2202,"y":445,"width":63,"height":78},"region_attributes":{"name":"R4"}},{"shape_attributes":{"name":"rect","x":2216,"y":520,"width":73,"height":61},"region_attributes":{"name":"R3"}},{"shape_attributes":{"name":"rect","x":2308,"y":455,"width":108,"height":106},"region_attributes":{"name":"Q2"}},{"shape_attributes":{"name":"rect","x":2442,"y":487,"width":106,"height":79},"region_attributes":{"name":"CR2"}},{"shape_attributes":{"name":"rect","x":2496,"y":396,"width":107,"height":107},"region_attributes":{"name":"Q1"}},{"shape_attributes":{"name":"rect","x":2584,"y":453,"width":106,"height":108},"region_attributes":{"name":"Q3"}},{"shape_attributes":{"name":"rect","x":2706,"y":532,"width":66,"height":49},"region_attributes":{"name":"FB2"}},{"shape_attributes":{"name":"rect","x":2643,"y":667,"width":103,"height":43},"region_attributes":{"name":"FB1"}},{"shape_attributes":{"name":"rect","x":2745,"y":733,"width":64,"height":57},"region_attributes":{"name":"FB3"}},{"shape_attributes":{"name":"rect","x":2536,"y":827,"width":82,"height":66},"region_attributes":{"name":"L2"}},{"shape_attributes":{"name":"rect","x":2065,"y":984,"width":51,"height":107},"region_attributes":{"name":"R43"}},{"shape_attributes":{"name":"rect","x":2107,"y":992,"width":50,"height":148},"region_attributes":{"name":"R44"}},{"shape_attributes":{"name":"rect","x":2147,"y":996,"width":71,"height":59},"region_attributes":{"name":"R45"}},{"shape_attributes":{"name":"rect","x":2622,"y":843,"width":66,"height":54},"region_attributes":{"name":"FB19"}},{"shape_attributes":{"name":"rect","x":1961,"y":1216,"width":56,"height":56},"region_attributes":{"name":"FB5"}},{"shape_attributes":{"name":"rect","x":2717,"y":2047,"width":89,"height":61},"region_attributes":{"name":"FB17"}},{"shape_attributes":{"name":"rect","x":2194,"y":2017,"width":81,"height":179},"region_attributes":{"name":"RP4"}},{"shape_attributes":{"name":"rect","x":2766,"y":2246,"width":87,"height":97},"region_attributes":{"name":"CR5"}},{"shape_attributes":{"name":"rect","x":2829,"y":2356,"width":126,"height":69},"region_attributes":{"name":"CR6"}},{"shape_attributes":{"name":"rect","x":2793,"y":2494,"width":154,"height":118},"region_attributes":{"name":"CR4"}},{"shape_attributes":{"name":"rect","x":2533,"y":2776,"width":88,"height":67},"region_attributes":{"name":"R39"}},{"shape_attributes":{"name":"rect","x":2490,"y":2839,"width":44,"height":117},"region_attributes":{"name":"FB20"}},{"shape_attributes":{"name":"rect","x":2528,"y":2839,"width":39,"height":116},"region_attributes":{"name":"FB21"}},{"shape_attributes":{"name":"rect","x":2039,"y":3043,"width":85,"height":73},"region_attributes":{"name":"R100"}},{"shape_attributes":{"name":"rect","x":2217,"y":3044,"width":61,"height":72},"region_attributes":{"name":"R5"}},{"shape_attributes":{"name":"rect","x":2047,"y":3134,"width":119,"height":88},"region_attributes":{"name":"CR1"}},{"shape_attributes":{"name":"rect","x":2829,"y":2857,"width":164,"height":82},"region_attributes":{"name":"L4"}},{"shape_attributes":{"name":"rect","x":3097,"y":2860,"width":106,"height":76},"region_attributes":{"name":"L5"}},{"shape_attributes":{"name":"rect","x":3075,"y":2217,"width":70,"height":77},"region_attributes":{"name":"R50"}},{"shape_attributes":{"name":"rect","x":3062,"y":2030,"width":84,"height":59},"region_attributes":{"name":"R34"}},{"shape_attributes":{"name":"rect","x":3494,"y":2030,"width":78,"height":57},"region_attributes":{"name":"R36"}},{"shape_attributes":{"name":"rect","x":2951,"y":1314,"width":87,"height":56},"region_attributes":{"name":"FB16"}},{"shape_attributes":{"name":"rect","x":3140,"y":1222,"width":78,"height":69},"region_attributes":{"name":"R52"}},{"shape_attributes":{"name":"rect","x":3137,"y":1152,"width":84,"height":60},"region_attributes":{"name":"R27"}},{"shape_attributes":{"name":"rect","x":3186,"y":883,"width":66,"height":36},"region_attributes":{"name":"E2"}},{"shape_attributes":{"name":"rect","x":3186,"y":919,"width":65,"height":36},"region_attributes":{"name":"E3"}},{"shape_attributes":{"name":"rect","x":2908,"y":902,"width":74,"height":66},"region_attributes":{"name":"R26"}},{"shape_attributes":{"name":"rect","x":3090,"y":902,"width":79,"height":67},"region_attributes":{"name":"R53"}},{"shape_attributes":{"name":"rect","x":4330,"y":1257,"width":78,"height":75},"region_attributes":{"name":"R16"}},{"shape_attributes":{"name":"rect","x":4299,"y":1311,"width":52,"height":75},"region_attributes":{"name":"R17"}},{"shape_attributes":{"name":"rect","x":4125,"y":1419,"width":106,"height":107},"region_attributes":{"name":"Q7"}},{"shape_attributes":{"name":"rect","x":4045,"y":1410,"width":65,"height":81},"region_attributes":{"name":"R19"}},{"shape_attributes":{"name":"rect","x":3252,"y":884,"width":51,"height":71},"region_attributes":{"name":"E1"}}],"file_attributes":{}}},"_via_attributes":{"region":{"name":{"type":"text","description":"","default_value":""}},"file":{}},"_via_data_format_version":"2.0.10","_via_image_id_list":["C64 250407 PCB Replica 1of2.jpg1200089"]}