{
  "_via_settings": {
    "ui": {
      "annotation_editor_height": 25,
      "annotation_editor_fontsize": 0.8,
      "leftsidebar_width": 17,
      "image_grid": {
        "img_height": 80,
        "rshape_fill": "none",
        "rshape_fill_opacity": 0.3,
        "rshape_stroke": "yellow",
        "rshape_stroke_width": 2,
        "show_region_shape": true,
        "show_image_policy": "all"
      },
      "image": {
        "region_label": "via_region_id",
        "region_color": "via_default_region_color",
        "region_label_font": "10px Sans",
        "on_image_annotation_editor_placement": "NEAR_REGION"
      }
    },
    "core": {
      "buffer_size": "18",
      "filepath": {},
      "default_filepath": ""
    },
    "project": {
      "name": "310378-1-left-and-right"
    }
  },
  "_via_img_metadata": {
    "310378-1-left-and-right.png139607": {
      "filename": "310378-1-left-and-right.png",
      "size": 139607,
      "regions": [
        {
          "shape_attributes": {
            "name": "rect",
            "x": 624,
            "y": 315,
            "width": 93,
            "height": 48
          },
          "region_attributes": {
            "name": "C86"
          }
        },
        {
          "shape_attributes": {
            "name": "rect",
            "x": 625,
            "y": 361,
            "width": 163,
            "height": 35
          },
          "region_attributes": {
            "name": "C5"
          }
        },
        {
          "shape_attributes": {
            "name": "rect",
            "x": 592,
            "y": 443,
            "width": 122,
            "height": 510
          },
          "region_attributes": {
            "name": "U5"
          }
        },
        {
          "shape_attributes": {
            "name": "rect",
            "x": 470,
            "y": 669,
            "width": 91,
            "height": 70
          },
          "region_attributes": {
            "name": "C108"
          }
        },
        {
          "shape_attributes": {
            "name": "rect",
            "x": 361,
            "y": 669,
            "width": 92,
            "height": 66
          },
          "region_attributes": {
            "name": "C109"
          }
        },
        {
          "shape_attributes": {
            "name": "rect",
            "x": 451,
            "y": 751,
            "width": 94,
            "height": 65
          },
          "region_attributes": {
            "name": "C83"
          }
        },
        {
          "shape_attributes": {
            "name": "rect",
            "x": 747,
            "y": 797,
            "width": 96,
            "height": 77
          },
          "region_attributes": {
            "name": "C82"
          }
        },
        {
          "shape_attributes": {
            "name": "rect",
            "x": 816,
            "y": 660,
            "width": 90,
            "height": 54
          },
          "region_attributes": {
            "name": "C81"
          }
        },
        {
          "shape_attributes": {
            "name": "rect",
            "x": 895,
            "y": 688,
            "width": 59,
            "height": 80
          },
          "region_attributes": {
            "name": "C112"
          }
        },
        {
          "shape_attributes": {
            "name": "rect",
            "x": 1011,
            "y": 486,
            "width": 107,
            "height": 96
          },
          "region_attributes": {
            "name": "C85"
          }
        },
        {
          "shape_attributes": {
            "name": "rect",
            "x": 1023,
            "y": 717,
            "width": 83,
            "height": 47
          },
          "region_attributes": {
            "name": "C84"
          }
        },
        {
          "shape_attributes": {
            "name": "rect",
            "x": 923,
            "y": 1395,
            "width": 79,
            "height": 74
          },
          "region_attributes": {
            "name": "C111"
          }
        },
        {
          "shape_attributes": {
            "name": "rect",
            "x": 858,
            "y": 1409,
            "width": 62,
            "height": 57
          },
          "region_attributes": {
            "name": "C116"
          }
        },
        {
          "shape_attributes": {
            "name": "rect",
            "x": 797,
            "y": 1372,
            "width": 83,
            "height": 40
          },
          "region_attributes": {
            "name": "U59"
          }
        },
        {
          "shape_attributes": {
            "name": "rect",
            "x": 749,
            "y": 1394,
            "width": 47,
            "height": 68
          },
          "region_attributes": {
            "name": "C115"
          }
        },
        {
          "shape_attributes": {
            "name": "rect",
            "x": 702,
            "y": 1391,
            "width": 43,
            "height": 70
          },
          "region_attributes": {
            "name": "C101"
          }
        },
        {
          "shape_attributes": {
            "name": "rect",
            "x": 658,
            "y": 1390,
            "width": 50,
            "height": 68
          },
          "region_attributes": {
            "name": "C105"
          }
        },
        {
          "shape_attributes": {
            "name": "rect",
            "x": 621,
            "y": 1513,
            "width": 124,
            "height": 80
          },
          "region_attributes": {
            "name": "C104"
          }
        },
        {
          "shape_attributes": {
            "name": "rect",
            "x": 926,
            "y": 1650,
            "width": 74,
            "height": 94
          },
          "region_attributes": {
            "name": "C106"
          }
        },
        {
          "shape_attributes": {
            "name": "rect",
            "x": 993,
            "y": 1670,
            "width": 54,
            "height": 83
          },
          "region_attributes": {
            "name": "C102"
          }
        },
        {
          "shape_attributes": {
            "name": "rect",
            "x": 236,
            "y": 1557,
            "width": 48,
            "height": 285
          },
          "region_attributes": {
            "name": "CN11"
          }
        },
        {
          "shape_attributes": {
            "name": "rect",
            "x": 297,
            "y": 1602,
            "width": 80,
            "height": 60
          },
          "region_attributes": {
            "name": "C95"
          }
        },
        {
          "shape_attributes": {
            "name": "rect",
            "x": 457,
            "y": 1574,
            "width": 81,
            "height": 62
          },
          "region_attributes": {
            "name": "C96"
          }
        },
        {
          "shape_attributes": {
            "name": "rect",
            "x": 457,
            "y": 1618,
            "width": 129,
            "height": 61
          },
          "region_attributes": {
            "name": "C97"
          }
        },
        {
          "shape_attributes": {
            "name": "rect",
            "x": 335,
            "y": 1734,
            "width": 85,
            "height": 71
          },
          "region_attributes": {
            "name": "C98"
          }
        },
        {
          "shape_attributes": {
            "name": "rect",
            "x": 461,
            "y": 1737,
            "width": 84,
            "height": 110
          },
          "region_attributes": {
            "name": "C99"
          }
        },
        {
          "shape_attributes": {
            "name": "rect",
            "x": 553,
            "y": 1694,
            "width": 59,
            "height": 77
          },
          "region_attributes": {
            "name": "C107"
          }
        },
        {
          "shape_attributes": {
            "name": "rect",
            "x": 620,
            "y": 1694,
            "width": 42,
            "height": 76
          },
          "region_attributes": {
            "name": "C103"
          }
        },
        {
          "shape_attributes": {
            "name": "rect",
            "x": 660,
            "y": 1728,
            "width": 58,
            "height": 51
          },
          "region_attributes": {
            "name": "C108"
          }
        },
        {
          "shape_attributes": {
            "name": "rect",
            "x": 235,
            "y": 1863,
            "width": 51,
            "height": 213
          },
          "region_attributes": {
            "name": "CN12"
          }
        },
        {
          "shape_attributes": {
            "name": "rect",
            "x": 811,
            "y": 1845,
            "width": 51,
            "height": 51
          },
          "region_attributes": {
            "name": "C3"
          }
        },
        {
          "shape_attributes": {
            "name": "rect",
            "x": 789,
            "y": 1945,
            "width": 99,
            "height": 203
          },
          "region_attributes": {
            "name": "U3"
          }
        },
        {
          "shape_attributes": {
            "name": "rect",
            "x": 917,
            "y": 2094,
            "width": 112,
            "height": 106
          },
          "region_attributes": {
            "name": "U31"
          }
        },
        {
          "shape_attributes": {
            "name": "rect",
            "x": 1258,
            "y": 1400,
            "width": 144,
            "height": 663
          },
          "region_attributes": {
            "name": "U7"
          }
        },
        {
          "shape_attributes": {
            "name": "rect",
            "x": 1180,
            "y": 1651,
            "width": 57,
            "height": 43
          },
          "region_attributes": {
            "name": "U54"
          }
        },
        {
          "shape_attributes": {
            "name": "rect",
            "x": 1179,
            "y": 1610,
            "width": 59,
            "height": 42
          },
          "region_attributes": {
            "name": "U54"
          }
        },
        {
          "shape_attributes": {
            "name": "rect",
            "x": 1606,
            "y": 1460,
            "width": 85,
            "height": 55
          },
          "region_attributes": {
            "name": "U61"
          }
        },
        {
          "shape_attributes": {
            "name": "rect",
            "x": 1235,
            "y": 1349,
            "width": 118,
            "height": 42
          },
          "region_attributes": {
            "name": "C77"
          }
        },
        {
          "shape_attributes": {
            "name": "rect",
            "x": 1306,
            "y": 1286,
            "width": 63,
            "height": 60
          },
          "region_attributes": {
            "name": "C7"
          }
        },
        {
          "shape_attributes": {
            "name": "rect",
            "x": 1629,
            "y": 875,
            "width": 86,
            "height": 59
          },
          "region_attributes": {
            "name": "U61"
          }
        },
        {
          "shape_attributes": {
            "name": "rect",
            "x": 1526,
            "y": 843,
            "width": 86,
            "height": 69
          },
          "region_attributes": {
            "name": "U61"
          }
        },
        {
          "shape_attributes": {
            "name": "rect",
            "x": 1609,
            "y": 794,
            "width": 92,
            "height": 63
          },
          "region_attributes": {
            "name": "U37"
          }
        },
        {
          "shape_attributes": {
            "name": "rect",
            "x": 1258,
            "y": 440,
            "width": 142,
            "height": 665
          },
          "region_attributes": {
            "name": "U6"
          }
        },
        {
          "shape_attributes": {
            "name": "rect",
            "x": 1417,
            "y": 705,
            "width": 80,
            "height": 58
          },
          "region_attributes": {
            "name": "U61"
          }
        },
        {
          "shape_attributes": {
            "name": "rect",
            "x": 1657,
            "y": 705,
            "width": 90,
            "height": 61
          },
          "region_attributes": {
            "name": "U37"
          }
        },
        {
          "shape_attributes": {
            "name": "rect",
            "x": 1576,
            "y": 668,
            "width": 97,
            "height": 67
          },
          "region_attributes": {
            "name": "U31"
          }
        },
        {
          "shape_attributes": {
            "name": "rect",
            "x": 1458,
            "y": 623,
            "width": 57,
            "height": 57
          },
          "region_attributes": {
            "name": "C68"
          }
        },
        {
          "shape_attributes": {
            "name": "rect",
            "x": 1580,
            "y": 603,
            "width": 95,
            "height": 61
          },
          "region_attributes": {
            "name": "U31"
          }
        },
        {
          "shape_attributes": {
            "name": "rect",
            "x": 1625,
            "y": 376,
            "width": 80,
            "height": 165
          },
          "region_attributes": {
            "name": "U56"
          }
        },
        {
          "shape_attributes": {
            "name": "rect",
            "x": 1220,
            "y": 387,
            "width": 125,
            "height": 45
          },
          "region_attributes": {
            "name": "C74"
          }
        },
        {
          "shape_attributes": {
            "name": "rect",
            "x": 1296,
            "y": 321,
            "width": 83,
            "height": 65
          },
          "region_attributes": {
            "name": "C6"
          }
        },
        {
          "shape_attributes": {
            "name": "rect",
            "x": 2076,
            "y": 369,
            "width": 143,
            "height": 530
          },
          "region_attributes": {
            "name": "U10"
          }
        },
        {
          "shape_attributes": {
            "name": "rect",
            "x": 2514,
            "y": 409,
            "width": 63,
            "height": 78
          },
          "region_attributes": {
            "name": "C12"
          }
        },
        {
          "shape_attributes": {
            "name": "rect",
            "x": 2267,
            "y": 445,
            "width": 77,
            "height": 57
          },
          "region_attributes": {
            "name": "C10"
          }
        },
        {
          "shape_attributes": {
            "name": "rect",
            "x": 2224,
            "y": 446,
            "width": 48,
            "height": 71
          },
          "region_attributes": {
            "name": "C110"
          }
        },
        {
          "shape_attributes": {
            "name": "rect",
            "x": 2485,
            "y": 530,
            "width": 100,
            "height": 205
          },
          "region_attributes": {
            "name": "U12"
          }
        },
        {
          "shape_attributes": {
            "name": "rect",
            "x": 2477,
            "y": 800,
            "width": 75,
            "height": 56
          },
          "region_attributes": {
            "name": "C13"
          }
        },
        {
          "shape_attributes": {
            "name": "rect",
            "x": 2484,
            "y": 901,
            "width": 100,
            "height": 202
          },
          "region_attributes": {
            "name": "U13"
          }
        },
        {
          "shape_attributes": {
            "name": "rect",
            "x": 1831,
            "y": 756,
            "width": 79,
            "height": 82
          },
          "region_attributes": {
            "name": "U60"
          }
        },
        {
          "shape_attributes": {
            "name": "rect",
            "x": 1794,
            "y": 927,
            "width": 54,
            "height": 87
          },
          "region_attributes": {
            "name": "U37"
          }
        },
        {
          "shape_attributes": {
            "name": "rect",
            "x": 1882,
            "y": 946,
            "width": 61,
            "height": 74
          },
          "region_attributes": {
            "name": "U57"
          }
        },
        {
          "shape_attributes": {
            "name": "rect",
            "x": 1788,
            "y": 1017,
            "width": 59,
            "height": 74
          },
          "region_attributes": {
            "name": "U8"
          }
        },
        {
          "shape_attributes": {
            "name": "rect",
            "x": 1883,
            "y": 1009,
            "width": 55,
            "height": 77
          },
          "region_attributes": {
            "name": "U8"
          }
        },
        {
          "shape_attributes": {
            "name": "rect",
            "x": 2241,
            "y": 967,
            "width": 51,
            "height": 71
          },
          "region_attributes": {
            "name": "C31"
          }
        },
        {
          "shape_attributes": {
            "name": "rect",
            "x": 2151,
            "y": 1035,
            "width": 115,
            "height": 77
          },
          "region_attributes": {
            "name": "U31"
          }
        },
        {
          "shape_attributes": {
            "name": "rect",
            "x": 2109,
            "y": 1330,
            "width": 75,
            "height": 42
          },
          "region_attributes": {
            "name": "C11"
          }
        },
        {
          "shape_attributes": {
            "name": "rect",
            "x": 2061,
            "y": 1371,
            "width": 99,
            "height": 37
          },
          "region_attributes": {
            "name": "C2"
          }
        },
        {
          "shape_attributes": {
            "name": "rect",
            "x": 2073,
            "y": 1419,
            "width": 142,
            "height": 715
          },
          "region_attributes": {
            "name": "U11"
          }
        },
        {
          "shape_attributes": {
            "name": "rect",
            "x": 2328,
            "y": 2035,
            "width": 146,
            "height": 89
          },
          "region_attributes": {
            "name": "U9"
          }
        },
        {
          "shape_attributes": {
            "name": "rect",
            "x": 2323,
            "y": 2136,
            "width": 146,
            "height": 106
          },
          "region_attributes": {
            "name": "U9"
          }
        },
        {
          "shape_attributes": {
            "name": "rect",
            "x": 3025,
            "y": 1508,
            "width": 102,
            "height": 84
          },
          "region_attributes": {
            "name": "U60"
          }
        },
        {
          "shape_attributes": {
            "name": "rect",
            "x": 3026,
            "y": 1415,
            "width": 102,
            "height": 83
          },
          "region_attributes": {
            "name": "U60"
          }
        },
        {
          "shape_attributes": {
            "name": "rect",
            "x": 2580,
            "y": 1349,
            "width": 83,
            "height": 46
          },
          "region_attributes": {
            "name": "C37"
          }
        },
        {
          "shape_attributes": {
            "name": "rect",
            "x": 2561,
            "y": 1145,
            "width": 97,
            "height": 77
          },
          "region_attributes": {
            "name": "U29"
          }
        },
        {
          "shape_attributes": {
            "name": "rect",
            "x": 2893,
            "y": 929,
            "width": 100,
            "height": 206
          },
          "region_attributes": {
            "name": "U15"
          }
        },
        {
          "shape_attributes": {
            "name": "rect",
            "x": 2895,
            "y": 826,
            "width": 94,
            "height": 57
          },
          "region_attributes": {
            "name": "C15"
          }
        },
        {
          "shape_attributes": {
            "name": "rect",
            "x": 2894,
            "y": 552,
            "width": 100,
            "height": 206
          },
          "region_attributes": {
            "name": "U14"
          }
        },
        {
          "shape_attributes": {
            "name": "rect",
            "x": 2925,
            "y": 428,
            "width": 65,
            "height": 77
          },
          "region_attributes": {
            "name": "C14"
          }
        }
      ],
      "file_attributes": {}
    }
  },
  "_via_attributes": {
    "region": {
      "name": {
        "type": "text",
        "description": "",
        "default_value": ""
      }
    },
    "file": {}
  },
  "_via_data_format_version": "2.0.10",
  "_via_image_id_list": [
    "310378-1-left-and-right.png139607"
  ]
}